quaternionic/__init__.py
quaternionic/__version__.py
quaternionic/algebra.py
quaternionic/alignment.py
quaternionic/arrays.py
quaternionic/converters.py
quaternionic/distance.py
quaternionic/interpolation.py
quaternionic/properties.py
quaternionic/utilities.py
quaternionic-1.0.17.dist-info/METADATA
quaternionic-1.0.17.dist-info/WHEEL
quaternionic-1.0.17.dist-info/licenses/LICENSE
quaternionic-1.0.17.dist-info/RECORD
