Metadata-Version: 2.4
Name: quaternionic
Version: 1.0.17
Summary: Interpret numpy arrays as quaternionic arrays with numba acceleration
Project-URL: Homepage, https://github.com/moble/quaternionic
Project-URL: Documentation, https://quaternionic.readthedocs.io/
Author-email: Michael Boyle <michael.oliver.boyle@gmail.com>
License: The MIT License (MIT)
License-File: LICENSE
Classifier: Development Status :: 5 - Production/Stable
Classifier: Intended Audience :: Science/Research
Classifier: License :: OSI Approved :: MIT License
Classifier: Operating System :: OS Independent
Classifier: Programming Language :: Python :: 3
Classifier: Topic :: Scientific/Engineering :: Astronomy
Classifier: Topic :: Scientific/Engineering :: Physics
Requires-Python: >=3.8
Requires-Dist: numba>=0.55; implementation_name == 'cpython'
Requires-Dist: numpy>=1.20
Requires-Dist: scipy>=1.5
Provides-Extra: docs
Requires-Dist: mkdocs; extra == 'docs'
Requires-Dist: mktheapidocs; extra == 'docs'
Requires-Dist: pymdown-extensions; extra == 'docs'
